Metadata-Version: 2.1
Name: momopapa
Version: 2.2.10
Summary: Bigdata Analysis Utilities
Home-page: https://github.com/jihokwak/motive
Author: momopapa
Author-email: datamanage@hellonature.net
License: UNKNOWN
Platform: UNKNOWN
Classifier: Programming Language :: Python :: 3
Classifier: License :: OSI Approved :: MIT License
Classifier: Operating System :: OS Independent
Requires-Python: >=3.6
Requires-Dist: bcrypt (==3.1.7)
Requires-Dist: bleach (==3.1.3)
Requires-Dist: boto3 (==1.14.28)
Requires-Dist: botocore (==1.17.28)
Requires-Dist: certifi (==2019.11.28)
Requires-Dist: cffi (==1.14.0)
Requires-Dist: chardet (==3.0.4)
Requires-Dist: cryptography (==2.9.2)
Requires-Dist: docutils (==0.15.2)
Requires-Dist: elasticsearch (==7.8.0)
Requires-Dist: fsspec (==0.7.4)
Requires-Dist: idna (==2.9)
Requires-Dist: importlib-metadata (==1.5.0)
Requires-Dist: jmespath (==0.10.0)
Requires-Dist: keyring (==21.2.0)
Requires-Dist: numpy (==1.19.0)
Requires-Dist: pandas (==1.0.5)
Requires-Dist: paramiko (==2.7.1)
Requires-Dist: pkginfo (==1.5.0.1)
Requires-Dist: psycopg2-binary (==2.8.5)
Requires-Dist: pyarrow (==1.0.0)
Requires-Dist: pycparser (==2.20)
Requires-Dist: Pygments (==2.6.1)
Requires-Dist: PyMySQL (==0.10.0)
Requires-Dist: PyNaCl (==1.4.0)
Requires-Dist: python-dateutil (==2.8.1)
Requires-Dist: pytz (==2020.1)
Requires-Dist: readme-renderer (==24.0)
Requires-Dist: redis (==3.5.3)
Requires-Dist: requests (==2.23.0)
Requires-Dist: requests-toolbelt (==0.9.1)
Requires-Dist: s3fs (==0.4.2)
Requires-Dist: s3transfer (==0.3.3)
Requires-Dist: six (==1.14.0)
Requires-Dist: slacker (==0.14.0)
Requires-Dist: SQLAlchemy (==1.3.18)
Requires-Dist: sshtunnel (==0.1.5)
Requires-Dist: tqdm (==4.43.0)
Requires-Dist: urllib3 (==1.25.8)
Requires-Dist: webencodings (==0.5.1)
Requires-Dist: zipp (==3.1.0)
